robo_orchard_build/__init__.py
robo_orchard_build/version.py
robo_orchard_build/custom_build/__init__.py
robo_orchard_build/custom_build/backend.py
robo_orchard_build/ext/__init__.py
robo_orchard_build/ext/build_ext.py
robo_orchard_build/ext/lint.py
robo_orchard_build/ext/meson.py
robo_orchard_build/ext/protobuf.py
robo_orchard_build/ext/stubgen.py
robo_orchard_build/lint/__init__.py
robo_orchard_build/lint/cpp_lint.py
robo_orchard_build/utils/__init__.py
robo_orchard_build/utils/file.py
robo_orchard_build/utils/git.py
robo_orchard_build/utils/pip.py
robo_orchard_build/utils/topology.py
robo_orchard_build-0.1.4.dist-info/licenses/LICENSE
robo_orchard_build-0.1.4.dist-info/METADATA
robo_orchard_build-0.1.4.dist-info/WHEEL
robo_orchard_build-0.1.4.dist-info/entry_points.txt
robo_orchard_build-0.1.4.dist-info/top_level.txt
robo_orchard_build-0.1.4.dist-info/RECORD
